openplm/__init__.py
openplm/constant.py
openplm/apis/__init__.py
openplm/metrics/__init__.py
openplm/metrics/rouge.py
openplm/models/__init__.py
openplm/models/modeling_outputs.py
openplm/models/bertsum/__init__.py
openplm/models/bertsum/configuration_bertsum.py
openplm/models/bertsum/modeling_bertsum.py
openplm/models/bertsum/tokenization_bertsum.py
openplm/models/ltrbert/__init__.py
openplm/models/ltrbert/modeling_ltrbert.py
openplm/models/simcse/__init__.py
openplm/models/simcse/modeling_simcse.py
openplm/utils/__init__.py
openplm-0.3.0.dist-info/LICENSE
openplm-0.3.0.dist-info/METADATA
openplm-0.3.0.dist-info/WHEEL
openplm-0.3.0.dist-info/top_level.txt
openplm-0.3.0.dist-info/RECORD
