Metadata-Version: 2.1
Name: openplm
Version: 0.3.0
Summary: OpenNLP
Home-page: https://github.com/autoliuweijie/opennlp
Author: Weijie Liu
Author-email: autoliuweijie@163.com
License: UNKNOWN
Platform: UNKNOWN
Classifier: Programming Language :: Python :: 3
Classifier: License :: OSI Approved :: MIT License
Classifier: Operating System :: OS Independent
Requires-Python: >=3.6
Requires-Dist: torch (>=1.7.0)
Requires-Dist: transformers (>=4.8.1)
